geohelper/__init__.py
geohelper/bearing.py
geohelper/distance.py
geohelper-0.2.0.dist-info/DESCRIPTION.rst
geohelper-0.2.0.dist-info/METADATA
geohelper-0.2.0.dist-info/metadata.json
geohelper-0.2.0.dist-info/pbr.json
geohelper-0.2.0.dist-info/RECORD
geohelper-0.2.0.dist-info/top_level.txt
geohelper-0.2.0.dist-info/WHEEL
